about_package.py
pip_autoremove.py
extra/__init__.py
extra/extra_utils.py
extra/graph_utils.py
extra/importlib_utils.py
pip3_autoremove-2.0.1.dist-info/LICENSE
pip3_autoremove-2.0.1.dist-info/METADATA
pip3_autoremove-2.0.1.dist-info/WHEEL
pip3_autoremove-2.0.1.dist-info/entry_points.txt
pip3_autoremove-2.0.1.dist-info/top_level.txt
pip3_autoremove-2.0.1.dist-info/RECORD
