Metadata-Version: 2.1
Name: pip3-autoremove
Version: 2.0.1
Summary: Remove a package and its unused dependencies(Supports Python3)
Home-page: https://github.com/mrmarvel/pip3-autoremove
License: Apache License 2.0
Classifier: Development Status :: 4 - Beta
Classifier: Intended Audience :: Developers
Classifier: License :: OSI Approved :: Apache Software License
Classifier: Programming Language :: Python
Classifier: Programming Language :: Python :: 3
Classifier: Programming Language :: Python :: Implementation :: PyPy
License-File: LICENSE
Requires-Dist: pip
Requires-Dist: setuptools ; python_version < "3.8"
Requires-Dist: packaging ; python_version >= "3.8"
